LICENSE
README.md
setup.py
ics_utils/__init__.py
ics_utils.egg-info/PKG-INFO
ics_utils.egg-info/SOURCES.txt
ics_utils.egg-info/dependency_links.txt
ics_utils.egg-info/top_level.txt
ics_utils/tools/__init__.py
ics_utils/tools/file.py
ics_utils/tools/notification.py
ics_utils/tools/utils.py