Metadata-Version: 2.1
Name: ics-utils
Version: 0.0.6
Summary: 爬虫工具包
Home-page: https://github.com/StealDivinePower/ics_utils
Author: hanyanling
License: UNKNOWN
Platform: UNKNOWN
Requires: requests
Requires: pandas
Requires: openpyxl
Requires: lxml
Requires: xlsx2csv
Requires-Python: >=3.6
License-File: LICENSE
